<?xml version="1.0" encoding="UTF-8"?><!-- 
	$Id: bundle.xml 47160 2013-12-09 13:13:55Z hummelb $
	$Rev: 47160 $
	@levd.rating GREEN Hash: BA967D3CC57E711FF278B931B44C0B9F
-->
<bundle xmlns="http://conqat.cs.tum.edu/ns/bundle">
   <name>Database Bundle</name>
   <provider>The ConQAT Project</provider>
   <description>Code for handling database connections.</description>
   <version major="2013" minor="12"/>
   <requiresCore major="2013" minor="12"/>
   <dependsOn bundleId="org.conqat.engine.commons" major="2013" minor="12"/>
</bundle>